<?xml version="1.0" encoding="UTF-8"?>
<objects serializationModel="Studio.01.10.00">
    <object class="AudioFile" id="{762c9a14-0702-4d33-8878-138506f2ed8c}">
        <property name="assetPath">
            <value>SFX_Human_Footsteps_Encumberment_1-003.wav</value>
        </property>
        <property name="frequencyInKHz">
            <value>44.0999985</value>
        </property>
        <property name="channelCount">
            <value>1</value>
        </property>
        <property name="length">
            <value>2.2325170068027211</value>
        </property>
        <relationship name="masterAssetFolder">
            <destination>{8a769b60-34e6-4452-bad6-a8cd33ed7e6e}</destination>
        </relationship>
    </object>
</objects>
